nonebot_plugin_yareminder/__init__.py
nonebot_plugin_yareminder/command/__init__.py
nonebot_plugin_yareminder/command/alconna.py
nonebot_plugin_yareminder/command/command.py
nonebot_plugin_yareminder/models.py
nonebot_plugin_yareminder/service.py
nonebot_plugin_yareminder/utils.py
nonebot_plugin_yareminder-0.2.0.dist-info/LICENSE
nonebot_plugin_yareminder-0.2.0.dist-info/METADATA
nonebot_plugin_yareminder-0.2.0.dist-info/WHEEL
nonebot_plugin_yareminder-0.2.0.dist-info/RECORD
