Metadata-Version: 2.1
Name: nonebot-plugin-yareminder
Version: 0.2.0
Summary: Yet another nonebot reminder plugin, providing scheduled and repetitive task reminders with per-task configuration and check-in.
License: MIT
Author: Yaoyun Zhang
Author-email: yaoyun_zhang@outlook.com
Requires-Python: >=3.10,<4.0
Classifier: License :: OSI Approved :: MIT License
Classifier: Programming Language :: Python :: 3
Classifier: Programming Language :: Python :: 3.10
Classifier: Programming Language :: Python :: 3.11
Classifier: Programming Language :: Python :: 3.12
Requires-Dist: nonebot-plugin-alconna (>=0.43.0)
Requires-Dist: nonebot-plugin-apscheduler (>=0.4.0)
Requires-Dist: nonebot-plugin-orm[sqlite] (>=0.7.6,<0.8.0)
Requires-Dist: nonebot-plugin-send-anything-anywhere (>=0.6.0,!=0.7.0)
Requires-Dist: nonebot2 (>=2.3,<3.0)
Requires-Dist: pendulum (>=3.0.0,<4.0.0)
